sdcclient/__init__.py
sdcclient/_common.py
sdcclient/_monitor.py
sdcclient/_monitor_v1.py
sdcclient/_scanning.py
sdcclient/_secure.py
sdcclient/_secure_v1.py
sdcclient/ibm_auth_helper.py
sdcclient/monitor/__init__.py
sdcclient/monitor/_dashboards_v2.py
sdcclient/monitor/_dashboards_v3.py
sdcclient/monitor/_events_v1.py
sdcclient/monitor/_events_v2.py
sdcclient/monitor/dashboard_converters/__init__.py
sdcclient/monitor/dashboard_converters/_dashboard_scope.py
sdcclient/monitor/dashboard_converters/_dashboard_versions.py
sdcclient/secure/__init__.py
sdcclient/secure/_activity_audit_v1.py
sdcclient/secure/_falco_rules_files_old.py
sdcclient/secure/_policy_events_old.py
sdcclient/secure/_policy_events_v1.py
sdcclient/secure/_policy_v2.py
sdcclient/secure/scanning/__init__.py
sdcclient/secure/scanning/_alerts.py
sdcclient-1.0.0.dist-info/LICENSE.txt
sdcclient-1.0.0.dist-info/METADATA
sdcclient-1.0.0.dist-info/WHEEL
sdcclient-1.0.0.dist-info/RECORD
